timelens/__init__.py
timelens/am/__init__.py
timelens/am/am_inputs.py
timelens/am/am_penalty.py
timelens/am/am_result.py
timelens/am/am_trainer.py
timelens/am/am_utils.py
timelens/am/am_visualization.py
timelens/cnn/cnn_raw.py
timelens/cnn/cnn_utils.py
timelens/cnn/cnn_visualization.py
timelens/utils/__init__.py
timelens/utils/dtw.py
timelens/utils/hooks.py
timelens/utils/layer.py
timelens-0.2.0a0.dist-info/LICENSE
timelens-0.2.0a0.dist-info/METADATA
timelens-0.2.0a0.dist-info/WHEEL
timelens-0.2.0a0.dist-info/RECORD
