Metadata-Version: 2.1
Name: timelens
Version: 0.2.0a0
Summary: A tool to analyze and understand time series in convolutional neural networks
Author: j-milkovits
Author-email: j.milkovits.t@posteo.net
Requires-Python: >=3.9,<4.0
Classifier: Programming Language :: Python :: 3
Classifier: Programming Language :: Python :: 3.9
Classifier: Programming Language :: Python :: 3.10
Classifier: Programming Language :: Python :: 3.11
Requires-Dist: datashader (>=0.15.1,<0.16.0)
Requires-Dist: holoviews (>=1.17.0,<2.0.0)
Requires-Dist: matplotlib (>=3.7.2,<4.0.0)
Requires-Dist: numba (>=0.57.1,<0.58.0)
Requires-Dist: numpy (>=1.24,<2.0)
Requires-Dist: torch (>=2.0.1,<3.0.0)
Requires-Dist: torchaudio (>=2.0.2,<3.0.0)
Requires-Dist: torchvision (>=0.15.2,<0.16.0)
Requires-Dist: umap-learn (>=0.5.3,<0.6.0)
